{
  "total_points": 2,
  "matched_points": [
    {
      "field": "character",
      "point": "Ambitious yet cautious, skilled in using probing language.",
      "discovered": true,
      "round": 1,
      "side": "A"
    },
    {
      "field": "goal",
      "point": "To obtain B's opinions and information through indirect questioning while concealing competitive intentions to avoid a hostile impression, and to secure promotion-related information.",
      "discovered": true,
      "round": 1,
      "side": "A"
    }
  ]
}